{"skeleton":{"hash":"GcvsYaI9A5f7yN7giAJfP0pAIYY","spine":"3.6.53","width":33775.1,"height":753,"images":"./qys1/qys2/"},"bones":[{"name":"root"},{"name":"1","parent":"root","x":-0.03,"y":0.29},{"name":"2","parent":"1","x":0.16,"y":-4.74},{"name":"9","parent":"1","x":0.03,"y":-1.41},{"name":"guang","parent":"9"},{"name":"8","parent":"guang"},{"name":"10","parent":"8","x":-0.02,"y":0.17},{"name":"12","parent":"guang"},{"name":"13","parent":"1","x":206.04,"y":-48.04,"scaleX":0.723,"scaleY":0.614,"color":"06ff00ff"},{"name":"14","parent":"1","x":327.82,"y":10.72,"scaleX":0.621,"scaleY":0.578,"color":"00ff0aff"},{"name":"15","parent":"1","x":0.12,"y":-3.89},{"name":"16","parent":"1","x":-0.02,"y":-1.26},{"name":"17","parent":"12","x":-0.02,"y":0.17},{"name":"18","parent":"9","scaleX":121.493},{"name":"19","parent":"1","x":0.12,"y":-3.89,"scaleX":1.26,"scaleY":1.26},{"name":"16-1","parent":"16"},{"name":"14-1","parent":"16-1"},{"name":"14-2","parent":"16-1","rotation":-90},{"name":"14-3","parent":"16-1","rotation":180},{"name":"14-4","parent":"16-1","rotation":90},{"name":"20","parent":"1","x":262.89,"y":43.36,"scaleX":0.927,"scaleY":0.585,"color":"2dff00ff"},{"name":"21","parent":"1","x":-220.8,"y":27.23,"scaleX":0.589,"scaleY":0.507,"color":"2dff00ff"},{"name":"22","parent":"1","x":-268.08,"y":20.39,"scaleX":0.621,"scaleY":0.578,"color":"00ff0aff"},{"name":"21-1","parent":"19"},{"name":"21-2","parent":"19"},{"name":"qys","parent":"1","x":3.82,"y":-19.83},{"name":"x1","parent":"1","length":38.4,"rotation":-88.32,"x":-2.1,"y":53.4,"color":"ff0000ff"},{"name":"x2","parent":"1","length":32.82,"rotation":-93.95,"x":11.06,"y":70.24,"color":"06ff00ff"},{"name":"x3","parent":"1","length":33.89,"rotation":-91.91,"x":6.99,"y":82,"color":"806dffff"},{"name":"x4","parent":"1","length":38.4,"rotation":-88.32,"x":-2.1,"y":53.4,"color":"ff0000ff"},{"name":"x5","parent":"x2","length":45.19,"rotation":-9.05,"x":25.4,"y":-7.3,"color":"2fff3bff"},{"name":"x6","parent":"x2","length":106.11,"rotation":24.5,"x":14.25,"y":6.64,"color":"06ff00ff"},{"name":"x7","parent":"x3","length":73.12,"rotation":15.3,"x":13.39,"y":4.96,"color":"d681ffff"},{"name":"x8","parent":"x3","length":92.89,"rotation":-18.73,"x":21.7,"y":-7.18,"color":"eca8ffff"},{"name":"x9","parent":"1","length":38.4,"rotation":-88.32,"x":-2.1,"y":53.4,"color":"ff0000ff"},{"name":"x10","parent":"1","length":38.4,"rotation":-88.32,"x":-2.1,"y":53.4,"color":"ff0000ff"},{"name":"x11","parent":"1","length":38.4,"rotation":-88.32,"x":-2.1,"y":53.4,"color":"ff0000ff"},{"name":"x12","parent":"1","length":38.4,"rotation":-88.32,"x":-2.1,"y":53.4,"color":"ff0000ff"},{"name":"x13","parent":"1","length":38.4,"rotation":-88.32,"x":-2.1,"y":53.4,"color":"ff0000ff"},{"name":"x14","parent":"1","length":38.4,"rotation":-88.32,"x":-2.1,"y":53.4,"color":"ff0000ff"},{"name":"x15","parent":"1","length":38.4,"rotation":-88.32,"x":-2.1,"y":53.4,"color":"ff0000ff"},{"name":"x16","parent":"1","length":33.89,"rotation":-47.51,"x":6.99,"y":82,"color":"806dffff"},{"name":"x17","parent":"x16","length":73.12,"rotation":15.3,"x":13.39,"y":4.96,"color":"d681ffff"},{"name":"x18","parent":"x16","length":92.89,"rotation":-18.73,"x":21.7,"y":-7.18,"color":"eca8ffff"},{"name":"x19","parent":"1","length":32.82,"rotation":-122.75,"x":11.06,"y":70.24,"color":"06ff00ff"},{"name":"x20","parent":"x19","length":45.19,"rotation":-9.05,"x":25.4,"y":-7.3,"color":"2fff3bff"},{"name":"x21","parent":"x19","length":106.11,"rotation":24.5,"x":14.25,"y":6.64,"scaleX":0.86,"scaleY":0.86,"color":"06ff00ff"},{"name":"x22","parent":"1","length":33.89,"rotation":-10.31,"x":6.99,"y":82,"color":"806dffff"},{"name":"x23","parent":"x22","length":73.12,"rotation":15.3,"x":13.39,"y":4.96,"color":"d681ffff"},{"name":"x24","parent":"x22","length":92.89,"rotation":-18.73,"x":21.7,"y":-7.18,"color":"eca8ffff"},{"name":"x25","parent":"1","length":32.82,"rotation":-167.15,"x":11.06,"y":70.24,"color":"06ff00ff"},{"name":"x26","parent":"x25","length":45.19,"rotation":-9.05,"x":25.4,"y":-7.3,"color":"2fff3bff"},{"name":"x27","parent":"x25","length":106.11,"rotation":24.5,"x":14.25,"y":6.64,"color":"06ff00ff"},{"name":"x28","parent":"1","length":33.89,"rotation":25.69,"x":6.99,"y":82,"color":"806dffff"},{"name":"x29","parent":"x28","length":73.12,"rotation":15.3,"x":13.39,"y":4.96,"color":"d681ffff"},{"name":"x30","parent":"x28","length":92.89,"rotation":-18.73,"x":21.7,"y":-7.18,"color":"eca8ffff"},{"name":"x31","parent":"1","length":33.89,"rotation":70.09,"x":6.99,"y":82,"color":"806dffff"},{"name":"x32","parent":"x31","length":73.12,"rotation":15.3,"x":13.39,"y":4.96,"color":"d681ffff"},{"name":"x33","parent":"x31","length":92.89,"rotation":-18.73,"x":21.7,"y":-7.18,"color":"eca8ffff"},{"name":"x34","parent":"1","length":33.89,"rotation":-160.31,"x":2.76,"y":33.58,"color":"806dffff"},{"name":"x35","parent":"x34","length":73.12,"rotation":15.3,"x":13.39,"y":4.96,"color":"d681ffff"},{"name":"x36","parent":"x34","length":92.89,"rotation":-18.73,"x":21.7,"y":-7.18,"color":"eca8ffff"},{"name":"x37","parent":"1","length":33.89,"rotation":-54.71,"x":5.59,"y":23.6,"color":"806dffff"},{"name":"x38","parent":"x37","length":73.12,"rotation":15.3,"x":13.39,"y":4.96,"color":"d681ffff"},{"name":"x39","parent":"x37","length":92.89,"rotation":-18.73,"x":21.7,"y":-7.18,"color":"eca8ffff"},{"name":"x40","parent":"1","length":33.89,"rotation":-117.11,"x":-16.24,"y":36.63,"color":"806dffff"},{"name":"x41","parent":"x40","length":73.12,"rotation":15.3,"x":13.39,"y":4.96,"color":"d681ffff"},{"name":"x42","parent":"x40","length":92.89,"rotation":-18.73,"x":21.7,"y":-7.18,"color":"eca8ffff"},{"name":"x43","parent":"1","length":32.82,"rotation":165.25,"x":11.06,"y":70.24,"color":"06ff00ff"},{"name":"x44","parent":"x43","length":45.19,"rotation":-9.05,"x":25.4,"y":-7.3,"color":"2fff3bff"},{"name":"x45","parent":"x43","length":106.11,"rotation":24.5,"x":14.25,"y":6.64,"color":"06ff00ff"},{"name":"x46","parent":"1","length":32.82,"rotation":-116.75,"x":11.06,"y":70.24,"color":"06ff00ff"},{"name":"x47","parent":"x46","length":45.19,"rotation":-9.05,"x":25.4,"y":-7.3,"color":"2fff3bff"},{"name":"x48","parent":"x46","length":106.11,"rotation":24.5,"x":14.25,"y":6.64,"scaleX":0.88,"scaleY":0.88,"color":"06ff00ff"},{"name":"x49","parent":"1","length":32.82,"rotation":-78.35,"x":11.06,"y":70.24,"color":"06ff00ff"},{"name":"x50","parent":"x49","length":45.19,"rotation":-9.05,"x":25.4,"y":-7.3,"color":"2fff3bff"},{"name":"x51","parent":"x49","length":106.11,"rotation":24.5,"x":14.25,"y":6.64,"color":"06ff00ff"},{"name":"x52","parent":"1","length":32.82,"rotation":-45.95,"x":-8.34,"y":51.48,"color":"06ff00ff"},{"name":"x53","parent":"x52","length":45.19,"rotation":-9.05,"x":25.4,"y":-7.3,"color":"2fff3bff"},{"name":"x54","parent":"x52","length":106.11,"rotation":24.5,"x":14.25,"y":6.64,"color":"06ff00ff"},{"name":"x55","parent":"1","length":32.82,"rotation":-143.15,"x":2.63,"y":0.98,"color":"06ff00ff"},{"name":"x56","parent":"x55","length":45.19,"rotation":-9.05,"x":25.4,"y":-7.3,"color":"2fff3bff"},{"name":"x57","parent":"x55","length":106.11,"rotation":24.5,"x":14.25,"y":6.64,"color":"06ff00ff"},{"name":"x58","parent":"1","length":32.82,"rotation":-45.95,"x":-8.34,"y":51.48,"color":"06ff00ff"},{"name":"x59","parent":"x58","length":45.19,"rotation":-9.05,"x":25.4,"y":-7.3,"color":"2fff3bff"},{"name":"x60","parent":"x58","length":106.11,"rotation":24.5,"x":14.25,"y":6.64,"scaleX":0.84,"scaleY":0.84,"color":"06ff00ff"},{"name":"x1-1","parent":"x1","length":73.39,"rotation":-1.68,"x":4.71,"y":6.64,"color":"ff3131ff"},{"name":"x1-2","parent":"x4","length":73.39,"rotation":-1.68,"x":4.71,"y":6.64,"color":"ff3131ff"},{"name":"x1-3","parent":"x9","length":73.39,"rotation":-1.68,"x":4.71,"y":6.64,"color":"ff3131ff"},{"name":"x1-4","parent":"x10","length":73.39,"rotation":-1.68,"x":4.71,"y":6.64,"color":"ff3131ff"},{"name":"x1-5","parent":"x11","length":73.39,"rotation":-1.68,"x":4.71,"y":6.64,"color":"ff3131ff"},{"name":"x1-6","parent":"x12","rotation":-1.68,"x":81.73,"y":2.76,"color":"ff3131ff"},{"name":"x1-7","parent":"x13","rotation":-1.68,"x":81.73,"y":2.76,"color":"ff3131ff"},{"name":"x1-8","parent":"x14","rotation":-1.68,"x":81.73,"y":2.76,"color":"ff3131ff"},{"name":"x1-9","parent":"x15","rotation":-1.68,"x":81.73,"y":2.76,"color":"ff3131ff"}],"slots":[{"name":"1","bone":"2"},{"name":"8","bone":"12","attachment":"8","blend":"additive"},{"name":"17","bone":"18","attachment":"8","blend":"additive"},{"name":"12","bone":"12","attachment":"8","blend":"additive"},{"name":"9","bone":"10","attachment":"9","blend":"additive"},{"name":"16","bone":"17","attachment":"9"},{"name":"13","bone":"13","attachment":"13","blend":"additive"},{"name":"23","bone":"14","attachment":"13","blend":"additive"},{"name":"26","bone":"22","attachment":"13","blend":"additive"},{"name":"24","bone":"20","attachment":"13","blend":"additive"},{"name":"25","bone":"21","attachment":"13","blend":"additive"},{"name":"14","bone":"14-1","attachment":"14","blend":"additive"},{"name":"18","bone":"14-2","attachment":"14","blend":"additive"},{"name":"19","bone":"14-3","attachment":"14","blend":"additive"},{"name":"20","bone":"14-4","attachment":"14","blend":"additive"},{"name":"15","bone":"15","attachment":"15","blend":"additive"},{"name":"21","bone":"21-1","attachment":"gq1","blend":"additive"},{"name":"22","bone":"21-2","attachment":"gq1","blend":"additive"},{"name":"x1","bone":"x1-1","attachment":"x1"},{"name":"x8","bone":"x1-4","attachment":"x1"},{"name":"x9","bone":"x1-5","attachment":"x1"},{"name":"x10","bone":"x1-6","attachment":"x1"},{"name":"x11","bone":"x1-7","attachment":"x1"},{"name":"x12","bone":"x1-8","attachment":"x1"},{"name":"x13","bone":"x1-9","attachment":"x1"},{"name":"x6","bone":"x1-2","attachment":"x1"},{"name":"x7","bone":"x1-3","attachment":"x1"},{"name":"x2","bone":"x5","attachment":"x2","blend":"additive"},{"name":"x16","bone":"x20","attachment":"x2","blend":"additive"},{"name":"x20","bone":"x26","attachment":"x2","blend":"additive"},{"name":"x32","bone":"x44","attachment":"x2","blend":"additive"},{"name":"x34","bone":"x47","attachment":"x2","blend":"additive"},{"name":"x36","bone":"x50","attachment":"x2","blend":"additive"},{"name":"x38","bone":"x53","attachment":"x2","blend":"additive"},{"name":"x42","bone":"x59","attachment":"x2","blend":"additive"},{"name":"x40","bone":"x56","attachment":"x2","blend":"additive"},{"name":"x5","bone":"x8","attachment":"x2","blend":"additive"},{"name":"x15","bone":"x18","attachment":"x2","blend":"additive"},{"name":"x19","bone":"x24","attachment":"x2","blend":"additive"},{"name":"x23","bone":"x30","attachment":"x2","blend":"additive"},{"name":"x25","bone":"x33","attachment":"x2","blend":"additive"},{"name":"x27","bone":"x36","attachment":"x2","blend":"additive"},{"name":"x29","bone":"x39","attachment":"x2","blend":"additive"},{"name":"x31","bone":"x42","attachment":"x2","blend":"additive"},{"name":"x3","bone":"x7","attachment":"x3","blend":"additive"},{"name":"x14","bone":"x17","attachment":"x3","blend":"additive"},{"name":"x18","bone":"x23","attachment":"x3","blend":"additive"},{"name":"x22","bone":"x29","attachment":"x3","blend":"additive"},{"name":"x24","bone":"x32","attachment":"x3","blend":"additive"},{"name":"x26","bone":"x35","attachment":"x3","blend":"additive"},{"name":"x28","bone":"x38","attachment":"x3","blend":"additive"},{"name":"x30","bone":"x41","attachment":"x3","blend":"additive"},{"name":"x4","bone":"x6","attachment":"x3","blend":"additive"},{"name":"x17","bone":"x21","attachment":"x3","blend":"additive"},{"name":"x21","bone":"x27","attachment":"x3","blend":"additive"},{"name":"x33","bone":"x45","attachment":"x3","blend":"additive"},{"name":"x35","bone":"x48","attachment":"x3","blend":"additive"},{"name":"x37","bone":"x51","attachment":"x3","blend":"additive"},{"name":"x39","bone":"x54","attachment":"x3","blend":"additive"},{"name":"x43","bone":"x60","attachment":"x3","blend":"additive"},{"name":"x41","bone":"x57","attachment":"x3","blend":"additive"},{"name":"qys","bone":"qys","attachment":"qys"}],"skins":{"default":{"12":{"8":{"x":-0.54,"y":-0.38,"width":278,"height":278}},"13":{"13":{"x":-6.78,"y":-0.26,"width":294,"height":15}},"14":{"14":{"x":69.02,"y":169.97,"width":371,"height":413}},"15":{"15":{"x":-0.12,"y":3.1,"width":349,"height":352}},"16":{"9":{"x":-0.52,"y":-0.55,"width":118,"height":118}},"17":{"8":{"x":-0.54,"y":-0.38,"width":278,"height":278}},"18":{"14":{"x":69.02,"y":169.97,"width":371,"height":413}},"19":{"14":{"x":69.02,"y":169.97,"width":371,"height":413}},"20":{"14":{"x":69.02,"y":169.97,"width":371,"height":413}},"21":{"gq1":{"x":-89.84,"y":3.1,"width":99,"height":221}},"22":{"gq1":{"x":92.86,"y":3.1,"scaleX":-1,"width":99,"height":221}},"23":{"13":{"x":-6.78,"y":-0.26,"width":294,"height":15}},"24":{"13":{"x":-6.78,"y":-0.26,"width":294,"height":15}},"25":{"13":{"x":-6.78,"y":-0.26,"width":294,"height":15}},"26":{"13":{"x":-6.78,"y":-0.26,"width":294,"height":15}},"8":{"8":{"x":-0.54,"y":-0.38,"width":278,"height":278}},"9":{"9":{"x":-0.52,"y":-0.55,"width":118,"height":118}},"qys":{"qys":{"x":-1.32,"y":-7.46,"width":292,"height":111}},"x1":{"x1":{"x":74.45,"y":-2.97,"rotation":90,"width":100,"height":70}},"x10":{"x1":{"x":-2.65,"y":-1.36,"rotation":90,"width":100,"height":70}},"x11":{"x1":{"x":-2.65,"y":-1.36,"rotation":90,"width":100,"height":70}},"x12":{"x1":{"x":-2.65,"y":-1.36,"rotation":90,"width":100,"height":70}},"x13":{"x1":{"x":-2.65,"y":-1.36,"rotation":90,"width":100,"height":70}},"x14":{"x3":{"x":106.03,"y":-9.62,"rotation":76.61,"width":84,"height":84}},"x15":{"x2":{"x":104.07,"y":-27.56,"rotation":110.64,"width":102,"height":102}},"x16":{"x2":{"x":67.19,"y":6.7,"rotation":102.99,"width":102,"height":102}},"x17":{"x3":{"x":110.32,"y":19.22,"rotation":69.44,"width":84,"height":84}},"x18":{"x3":{"x":106.03,"y":-9.62,"rotation":76.61,"width":84,"height":84}},"x19":{"x2":{"x":104.07,"y":-27.56,"rotation":110.64,"width":102,"height":102}},"x2":{"x2":{"x":40.06,"y":0.44,"rotation":102.99,"width":102,"height":102}},"x20":{"x2":{"x":67.19,"y":6.7,"rotation":102.99,"width":102,"height":102}},"x21":{"x3":{"x":110.32,"y":19.22,"rotation":69.44,"width":84,"height":84}},"x22":{"x3":{"x":106.03,"y":-9.62,"rotation":76.61,"width":84,"height":84}},"x23":{"x2":{"x":104.07,"y":-27.56,"rotation":110.64,"width":102,"height":102}},"x24":{"x3":{"x":106.03,"y":-9.62,"rotation":76.61,"width":84,"height":84}},"x25":{"x2":{"x":104.07,"y":-27.56,"rotation":110.64,"width":102,"height":102}},"x26":{"x3":{"x":106.03,"y":-9.62,"rotation":76.61,"width":84,"height":84}},"x27":{"x2":{"x":104.07,"y":-27.56,"rotation":110.64,"width":102,"height":102}},"x28":{"x3":{"x":106.03,"y":-9.62,"rotation":76.61,"width":84,"height":84}},"x29":{"x2":{"x":104.07,"y":-27.56,"rotation":110.64,"width":102,"height":102}},"x3":{"x3":{"x":72.18,"y":-1.56,"rotation":76.61,"width":84,"height":84}},"x30":{"x3":{"x":106.03,"y":-9.62,"rotation":76.61,"width":84,"height":84}},"x31":{"x2":{"x":104.07,"y":-27.56,"rotation":110.64,"width":102,"height":102}},"x32":{"x2":{"x":67.19,"y":6.7,"rotation":102.99,"width":102,"height":102}},"x33":{"x3":{"x":110.32,"y":19.22,"rotation":69.44,"width":84,"height":84}},"x34":{"x2":{"x":67.19,"y":6.7,"rotation":102.99,"width":102,"height":102}},"x35":{"x3":{"x":110.32,"y":19.22,"rotation":69.44,"width":84,"height":84}},"x36":{"x2":{"x":67.19,"y":6.7,"rotation":102.99,"width":102,"height":102}},"x37":{"x3":{"x":110.32,"y":19.22,"rotation":69.44,"width":84,"height":84}},"x38":{"x2":{"x":67.19,"y":6.7,"rotation":102.99,"width":102,"height":102}},"x39":{"x3":{"x":110.32,"y":19.22,"rotation":69.44,"width":84,"height":84}},"x4":{"x3":{"x":103.27,"y":0.41,"rotation":69.44,"width":84,"height":84}},"x40":{"x2":{"x":67.19,"y":6.7,"rotation":102.99,"width":102,"height":102}},"x41":{"x3":{"x":110.32,"y":19.22,"rotation":69.44,"width":84,"height":84}},"x42":{"x2":{"x":67.19,"y":6.7,"rotation":102.99,"width":102,"height":102}},"x43":{"x3":{"x":110.32,"y":19.22,"rotation":69.44,"width":84,"height":84}},"x5":{"x2":{"x":93.43,"y":0.69,"rotation":110.64,"width":102,"height":102}},"x6":{"x1":{"x":74.45,"y":-2.97,"rotation":90,"width":100,"height":70}},"x7":{"x1":{"x":74.45,"y":-2.97,"rotation":90,"width":100,"height":70}},"x8":{"x1":{"x":74.45,"y":-2.97,"rotation":90,"width":100,"height":70}},"x9":{"x1":{"x":74.45,"y":-2.97,"rotation":90,"width":100,"height":70}}}},"animations":{"animation":{"slots":{"8":{"color":[{"time":0,"color":"ffffff53"},{"time":0.3,"color":"ffffffff","curve":"stepped"},{"time":1,"color":"ffffffff"},{"time":1.0333,"color":"ffffff00"}]},"9":{"color":[{"time":0,"color":"ffffff37","curve":"stepped"},{"time":0.5,"color":"ffffff37"},{"time":0.6667,"color":"ffffff00"}]},"12":{"color":[{"time":0,"color":"ffffff00"},{"time":0.3,"color":"ffffff0e"}]},"13":{"color":[{"time":0,"color":"ffffff00","curve":"stepped"},{"time":0.6667,"color":"ffffff00"},{"time":0.7,"color":"ffffffff"},{"time":1.2667,"color":"ffffff00","curve":"stepped"},{"time":1.4667,"color":"ffffff00"}]},"14":{"color":[{"time":0,"color":"ffffff00"},{"time":0.2667,"color":"ffffff4b"},{"time":0.4333,"color":"ffffff00"}]},"15":{"color":[{"time":0,"color":"ffffff00"},{"time":0.4667,"color":"ffffff51"},{"time":0.6333,"color":"ffffff00"}]},"16":{"color":[{"time":0,"color":"ffffffff"},{"time":0.3,"color":"ffffffa3"},{"time":0.4667,"color":"ffffffda","curve":"stepped"},{"time":0.5667,"color":"ffffffda"},{"time":0.6667,"color":"ffffff00","curve":"stepped"},{"time":1,"color":"ffffff00","curve":"stepped"},{"time":1.0333,"color":"ffffff00"}]},"17":{"color":[{"time":0,"color":"ffffff45"},{"time":0.4667,"color":"ffffff00","curve":"stepped"},{"time":0.6667,"color":"ffffff00"}]},"18":{"color":[{"time":0,"color":"ffffff00"},{"time":0.2667,"color":"ffffff4b"},{"time":0.4333,"color":"ffffff00"}]},"19":{"color":[{"time":0,"color":"ffffff00"},{"time":0.2667,"color":"ffffff4b"},{"time":0.4333,"color":"ffffff00"}]},"20":{"color":[{"time":0,"color":"ffffff00"},{"time":0.2667,"color":"ffffff4b"},{"time":0.4333,"color":"ffffff00"}]},"21":{"color":[{"time":0,"color":"ffffff00"},{"time":0.3333,"color":"ffffff27"},{"time":0.4333,"color":"ffffff00"}]},"22":{"color":[{"time":0,"color":"ffffff00"},{"time":0.3333,"color":"ffffff27"},{"time":0.4333,"color":"ffffff00"}]},"23":{"color":[{"time":0,"color":"ffffff00","curve":"stepped"},{"time":0.6667,"color":"ffffff00"},{"time":0.7,"color":"ffffffff"},{"time":1.1,"color":"ffffff00","curve":"stepped"},{"time":1.4667,"color":"ffffff00"}]},"24":{"color":[{"time":0,"color":"ffffff00","curve":"stepped"},{"time":0.6667,"color":"ffffff00"},{"time":0.7,"color":"ffffffff"},{"time":1.0333,"color":"ffffff00","curve":"stepped"},{"time":1.4667,"color":"ffffff00"}]},"25":{"color":[{"time":0,"color":"ffffff00","curve":"stepped"},{"time":0.6667,"color":"ffffff00"},{"time":0.7,"color":"ffffffff"},{"time":1.1,"color":"ffffff00","curve":"stepped"},{"time":1.4667,"color":"ffffff00"}]},"26":{"color":[{"time":0,"color":"ffffff00","curve":"stepped"},{"time":0.6667,"color":"ffffff00"},{"time":0.7,"color":"ffffffff"},{"time":1.1667,"color":"ffffff00","curve":"stepped"},{"time":1.4667,"color":"ffffff00"}]},"qys":{"color":[{"time":0,"color":"ffffff00","curve":"stepped"},{"time":0.2333,"color":"ffffff00"},{"time":0.4333,"color":"ffffffff","curve":"stepped"},{"time":1.1667,"color":"ffffffff"},{"time":1.4667,"color":"ffffff00"}]},"x1":{"color":[{"time":0,"color":"ffffff00","curve":"stepped"},{"time":0.2667,"color":"ffffff00"},{"time":0.6667,"color":"ffffffff","curve":"stepped"},{"time":0.9667,"color":"ffffffff"},{"time":1.3333,"color":"ffffff00","curve":"stepped"},{"time":1.4667,"color":"ffffff00"}]},"x6":{"color":[{"time":0,"color":"ffffff00","curve":"stepped"},{"time":0.2667,"color":"ffffff00"},{"time":0.6667,"color":"ffffffff","curve":"stepped"},{"time":0.9,"color":"ffffffff"},{"time":1.3333,"color":"ffffff00","curve":"stepped"},{"time":1.4667,"color":"ffffff00"}]},"x7":{"color":[{"time":0,"color":"ffffff00","curve":"stepped"},{"time":0.2667,"color":"ffffff00"},{"time":0.5,"color":"ffffffff","curve":"stepped"},{"time":0.8333,"color":"ffffffff"},{"time":1.4333,"color":"ffffff00","curve":"stepped"},{"time":1.4667,"color":"ffffff00"}]},"x8":{"color":[{"time":0,"color":"ffffff00","curve":"stepped"},{"time":0.2667,"color":"ffffff00"},{"time":0.6667,"color":"ffffffff","curve":"stepped"},{"time":0.9667,"color":"ffffffff"},{"time":1.4333,"color":"ffffff00","curve":"stepped"},{"time":1.4667,"color":"ffffff00"}]},"x9":{"color":[{"time":0,"color":"ffffff00","curve":"stepped"},{"time":0.2667,"color":"ffffff00"},{"time":0.6667,"color":"ffffffff","curve":"stepped"},{"time":0.9667,"color":"ffffffff"},{"time":1.3333,"color":"ffffff00","curve":"stepped"},{"time":1.4667,"color":"ffffff00"}]},"x10":{"color":[{"time":0,"color":"ffffff00","curve":"stepped"},{"time":0.4,"color":"ffffff00"},{"time":0.8333,"color":"ffffffff","curve":"stepped"},{"time":0.9667,"color":"ffffffff"},{"time":1.4667,"color":"ffffff00"}]},"x11":{"color":[{"time":0,"color":"ffffff00","curve":"stepped"},{"time":0.4,"color":"ffffff00"},{"time":0.8333,"color":"ffffffff","curve":"stepped"},{"time":0.9667,"color":"ffffffff"},{"time":1.4667,"color":"ffffff00"}]},"x12":{"color":[{"time":0,"color":"ffffff00","curve":"stepped"},{"time":0.4,"color":"ffffff00"},{"time":0.8333,"color":"ffffffff","curve":"stepped"},{"time":0.9667,"color":"ffffffff"},{"time":1.3,"color":"ffffff00","curve":"stepped"},{"time":1.4667,"color":"ffffff00"}]},"x13":{"color":[{"time":0,"color":"ffffff00","curve":"stepped"},{"time":0.4,"color":"ffffff00"},{"time":0.8333,"color":"ffffffff","curve":"stepped"},{"time":0.9667,"color":"ffffffff"},{"time":1.4,"color":"ffffff00","curve":"stepped"},{"time":1.4667,"color":"ffffff00"}]},"x14":{"color":[{"time":0,"color":"ffffff00","curve":"stepped"},{"time":0.5,"color":"ffffff00"},{"time":0.6667,"color":"ffffffff"}]},"x15":{"color":[{"time":0,"color":"ffffff00","curve":"stepped"},{"time":0.5,"color":"ffffff00"},{"time":0.6667,"color":"ffffffff"}]},"x16":{"color":[{"time":0,"color":"ffffff00","curve":"stepped"},{"time":0.5,"color":"ffffff00"},{"time":0.6667,"color":"ffffffff"}]},"x17":{"color":[{"time":0,"color":"ffffff00","curve":"stepped"},{"time":0.5,"color":"ffffff00"},{"time":0.6667,"color":"ffffffff"}]},"x18":{"color":[{"time":0,"color":"ffffff00","curve":"stepped"},{"time":0.5,"color":"ffffff00"},{"time":0.6667,"color":"ffffffff"}]},"x19":{"color":[{"time":0,"color":"ffffff00","curve":"stepped"},{"time":0.5,"color":"ffffff00"},{"time":0.6667,"color":"ffffffff"}]},"x20":{"color":[{"time":0,"color":"ffffff00","curve":"stepped"},{"time":0.5,"color":"ffffff00"},{"time":0.6667,"color":"ffffffff"}]},"x21":{"color":[{"time":0,"color":"ffffff00","curve":"stepped"},{"time":0.5,"color":"ffffff00"},{"time":0.6667,"color":"ffffffff"}]},"x22":{"color":[{"time":0,"color":"ffffff00","curve":"stepped"},{"time":0.5,"color":"ffffff00"},{"time":0.6667,"color":"ffffffff"}]},"x23":{"color":[{"time":0,"color":"ffffff00","curve":"stepped"},{"time":0.5,"color":"ffffff00"},{"time":0.6667,"color":"ffffffff"}]},"x24":{"color":[{"time":0,"color":"ffffff00","curve":"stepped"},{"time":0.5,"color":"ffffff00"},{"time":0.6667,"color":"ffffffff"}]},"x25":{"color":[{"time":0,"color":"ffffff00","curve":"stepped"},{"time":0.5,"color":"ffffff00"},{"time":0.6667,"color":"ffffffff"}]},"x26":{"color":[{"time":0,"color":"ffffff00","curve":"stepped"},{"time":0.5,"color":"ffffff00"},{"time":0.6667,"color":"ffffffff"}]},"x27":{"color":[{"time":0,"color":"ffffff00","curve":"stepped"},{"time":0.5,"color":"ffffff00"},{"time":0.6667,"color":"ffffffff"}]},"x28":{"color":[{"time":0,"color":"ffffff00","curve":"stepped"},{"time":0.5,"color":"ffffff00"},{"time":0.6667,"color":"ffffffff"}]},"x29":{"color":[{"time":0,"color":"ffffff00","curve":"stepped"},{"time":0.5,"color":"ffffff00"},{"time":0.6667,"color":"ffffffff"}]},"x30":{"color":[{"time":0,"color":"ffffff00","curve":"stepped"},{"time":0.5,"color":"ffffff00"},{"time":0.6667,"color":"ffffffff"}]},"x31":{"color":[{"time":0,"color":"ffffff00","curve":"stepped"},{"time":0.5,"color":"ffffff00"},{"time":0.6667,"color":"ffffffff"}]},"x32":{"color":[{"time":0,"color":"ffffff00","curve":"stepped"},{"time":0.5,"color":"ffffff00"},{"time":0.6667,"color":"ffffffff"}]},"x33":{"color":[{"time":0,"color":"ffffff00","curve":"stepped"},{"time":0.5,"color":"ffffff00"},{"time":0.6667,"color":"ffffffff"}]},"x34":{"color":[{"time":0,"color":"ffffff00","curve":"stepped"},{"time":0.5,"color":"ffffff00"},{"time":0.6667,"color":"ffffffff"}]},"x35":{"color":[{"time":0,"color":"ffffff00","curve":"stepped"},{"time":0.5,"color":"ffffff00"},{"time":0.6667,"color":"ffffffff"}]},"x36":{"color":[{"time":0,"color":"ffffff00","curve":"stepped"},{"time":0.5,"color":"ffffff00"},{"time":0.6667,"color":"ffffffff"}]},"x37":{"color":[{"time":0,"color":"ffffff00","curve":"stepped"},{"time":0.5,"color":"ffffff00"},{"time":0.6667,"color":"ffffffff"}]},"x38":{"color":[{"time":0,"color":"ffffff00","curve":"stepped"},{"time":0.5,"color":"ffffff00"},{"time":0.6667,"color":"ffffffff"}]},"x39":{"color":[{"time":0,"color":"ffffff00","curve":"stepped"},{"time":0.5,"color":"ffffff00"},{"time":0.6667,"color":"ffffffff"}]},"x40":{"color":[{"time":0,"color":"ffffff00","curve":"stepped"},{"time":0.5,"color":"ffffff00"},{"time":0.6667,"color":"ffffffff"}]},"x41":{"color":[{"time":0,"color":"ffffff00","curve":"stepped"},{"time":0.5,"color":"ffffff00"},{"time":0.6667,"color":"ffffffff"}]},"x42":{"color":[{"time":0,"color":"ffffff00","curve":"stepped"},{"time":0.5,"color":"ffffff00"},{"time":0.6667,"color":"ffffffff"}]},"x43":{"color":[{"time":0,"color":"ffffff00","curve":"stepped"},{"time":0.5,"color":"ffffff00"},{"time":0.6667,"color":"ffffffff"}]}},"bones":{"18":{"scale":[{"time":0.4667,"x":1.901,"y":1.277},{"time":0.5,"x":1.901,"y":0.739},{"time":0.6667,"x":1.901,"y":0.444},{"time":0.8333,"x":1.901,"y":0}]},"guang":{"scale":[{"time":0,"x":3.213,"y":1.311},{"time":0.3,"x":5.898,"y":1.311},{"time":0.5,"x":121.49,"y":1},{"time":0.8333,"x":121.49,"y":0.148},{"time":1,"x":121.49,"y":0.004}]},"8":{"scale":[{"time":0,"x":2.07,"y":1.93},{"time":0.3,"x":2.066,"y":1.934}]},"10":{"scale":[{"time":0,"x":1,"y":1,"curve":"stepped"},{"time":0.4667,"x":1,"y":1},{"time":0.5,"x":1,"y":0.577},{"time":0.6667,"x":1,"y":0.107}]},"17":{"scale":[{"time":0,"x":1.901,"y":2.049,"curve":"stepped"},{"time":0.3,"x":1.901,"y":2.049},{"time":0.4667,"x":1.901,"y":1.277},{"time":0.5,"x":1.901,"y":0.739},{"time":0.6667,"x":1.901,"y":0.444}]},"qys":{"translate":[{"time":0,"x":0,"y":22.58}],"scale":[{"time":0.2333,"x":0.5,"y":0.5},{"time":0.4333,"x":1.14,"y":1.14},{"time":0.5333,"x":0.9,"y":0.9},{"time":0.6333,"x":1,"y":1}]},"19":{"scale":[{"time":0,"x":1,"y":1},{"time":0.4333,"x":2.22,"y":2.319}]},"21-1":{"translate":[{"time":0,"x":0,"y":0},{"time":0.4333,"x":-83.55,"y":0}]},"21-2":{"translate":[{"time":0,"x":0,"y":0},{"time":0.4333,"x":87.42,"y":0}]},"16-1":{"rotate":[{"time":0,"angle":0},{"time":0.4333,"angle":-90}],"scale":[{"time":0,"x":0.35,"y":0.351},{"time":0.4333,"x":1,"y":1}]},"15":{"scale":[{"time":0,"x":0.502,"y":0.502},{"time":0.6667,"x":1.649,"y":1.649}]},"x2":{"rotate":[{"time":0,"angle":177.6}],"translate":[{"time":0,"x":-9.96,"y":-143.78,"curve":"stepped"},{"time":0.6667,"x":-9.96,"y":-143.78},{"time":1.4667,"x":381.32,"y":-89.78}]},"x1":{"rotate":[{"time":0,"angle":-91.2},{"time":0.8,"angle":180},{"time":1.4333,"angle":88.8},{"time":1.4667,"angle":-91.2}],"translate":[{"time":0,"x":0,"y":0,"curve":"stepped"},{"time":0.2333,"x":0,"y":0,"curve":[0.25,0,0.75,1]},{"time":1.4333,"x":524.44,"y":-179.9},{"time":1.4667,"x":0,"y":0}]},"x3":{"rotate":[{"time":0,"angle":144,"curve":"stepped"},{"time":0.6667,"angle":144},{"time":1.0667,"angle":249.6},{"time":1.4667,"angle":-26.4}],"translate":[{"time":0,"x":-85.62,"y":-133.24,"curve":"stepped"},{"time":0.6667,"x":-85.62,"y":-133.24},{"time":1.4667,"x":-347.99,"y":-129.92}]},"x1-1":{"rotate":[{"time":0,"angle":68.4},{"time":0.6667,"angle":19.2},{"time":1.4333,"angle":-22.8},{"time":1.4667,"angle":19.2}]},"x1-2":{"rotate":[{"time":0,"angle":19.2},{"time":1.4333,"angle":-22.8},{"time":1.4667,"angle":19.2}]},"x4":{"rotate":[{"time":0,"angle":-91.2},{"time":0.8,"angle":180},{"time":1.4333,"angle":88.8},{"time":1.4667,"angle":-91.2}],"translate":[{"time":0,"x":0,"y":0,"curve":"stepped"},{"time":0.2333,"x":0,"y":0,"curve":[0.25,0,0.75,1]},{"time":1.4333,"x":-2.25,"y":-270},{"time":1.4667,"x":0,"y":0}]},"x1-3":{"rotate":[{"time":0,"angle":19.2},{"time":1.4333,"angle":-16.8},{"time":1.4667,"angle":19.2}]},"x9":{"rotate":[{"time":0,"angle":-91.2},{"time":0.8,"angle":180},{"time":1.4333,"angle":88.8},{"time":1.4667,"angle":-91.2}],"translate":[{"time":0,"x":193.82,"y":-116.14,"curve":[0.379,0.6,0.724,1]},{"time":0.5,"x":44.65,"y":-102.93,"curve":[0.242,0,0.667,0.67]},{"time":1.4667,"x":193.82,"y":-116.14}]},"x1-4":{"rotate":[{"time":0,"angle":178.32},{"time":0.8,"angle":259.2},{"time":1.4333,"angle":-14.4},{"time":1.4667,"angle":-91.2}]},"x10":{"translate":[{"time":0,"x":0,"y":0,"curve":"stepped"},{"time":0.2333,"x":0,"y":0,"curve":[0.25,0,0.75,1]},{"time":1.4333,"x":-390.24,"y":-187.56},{"time":1.4667,"x":0,"y":0}]},"x1-5":{"rotate":[{"time":0,"angle":124.31},{"time":0.8,"angle":-56.41},{"time":1.4333,"angle":4.79},{"time":1.4667,"angle":-91.2}]},"x11":{"translate":[{"time":0,"x":-228.27,"y":-202.71,"curve":[0.379,0.6,0.724,1]},{"time":0.3,"x":-279.91,"y":-248.57},{"time":0.3333,"x":0,"y":0,"curve":"stepped"},{"time":0.5667,"x":0,"y":0,"curve":[0.242,0,0.667,0.67]},{"time":1.4667,"x":-228.27,"y":-202.71}]},"x1-6":{"rotate":[{"time":0,"angle":124.31},{"time":0.8,"angle":-84.01},{"time":1.4667,"angle":-66.01}]},"x12":{"translate":[{"time":0,"x":-49.78,"y":13.32,"curve":[0.308,0.24,0.648,0.6]},{"time":0.5333,"x":-51.3,"y":65.07,"curve":[0.308,0.24,0.648,0.6]},{"time":1.4667,"x":-325.44,"y":-175.71}]},"x1-7":{"rotate":[{"time":0,"angle":124.31},{"time":0.4,"angle":-84.01},{"time":0.8333,"angle":1.3},{"time":1.2,"angle":93.13},{"time":1.4667,"angle":172.33}]},"x13":{"rotate":[{"time":0,"angle":174}],"translate":[{"time":0,"x":-49.78,"y":13.32,"curve":[0.308,0.24,0.648,0.6]},{"time":0.5333,"x":-51.3,"y":65.07,"curve":[0.318,0.27,0.653,0.61]},{"time":1.4667,"x":-491.09,"y":-51.65}]},"x1-8":{"rotate":[{"time":0,"angle":124.31},{"time":0.4,"angle":-84.01},{"time":0.8333,"angle":1.3},{"time":1.2,"angle":93.13},{"time":1.4667,"angle":172.33}],"scale":[{"time":0,"x":0.747,"y":0.689},{"time":1.4667,"x":0.511,"y":0.502}]},"x14":{"rotate":[{"time":0,"angle":103.2}],"translate":[{"time":0,"x":-49.78,"y":13.32,"curve":[0.308,0.24,0.648,0.6]},{"time":0.5333,"x":-51.3,"y":65.07,"curve":[0.321,0.28,0.655,0.62]},{"time":1.4667,"x":396.11,"y":135.78}]},"x1-9":{"rotate":[{"time":0,"angle":124.31},{"time":0.4,"angle":-84.01},{"time":0.8333,"angle":1.3},{"time":1.2,"angle":93.13},{"time":1.4667,"angle":172.33}],"scale":[{"time":0,"x":0.584,"y":0.595},{"time":1.4667,"x":0.43,"y":0.418}]},"x15":{"rotate":[{"time":0,"angle":46.8}],"translate":[{"time":0,"x":-49.78,"y":13.32,"curve":[0.308,0.24,0.648,0.6]},{"time":0.5333,"x":-51.3,"y":65.07,"curve":[0.321,0.28,0.655,0.62]},{"time":1.4667,"x":401.73,"y":88.21}]},"x7":{"rotate":[{"time":0,"angle":-15.6,"curve":"stepped"},{"time":0.6333,"angle":-15.6},{"time":0.6667,"angle":-58.8},{"time":1.4667,"angle":-33.3}],"translate":[{"time":0.6667,"x":0,"y":0},{"time":1.4667,"x":47.55,"y":-15.45}],"scale":[{"time":0,"x":0,"y":0,"curve":"stepped"},{"time":0.6333,"x":0,"y":0},{"time":0.6667,"x":0.7,"y":0.7},{"time":1,"x":0.52,"y":0.46},{"time":1.2667,"x":0,"y":0,"curve":"stepped"},{"time":1.4667,"x":0,"y":0}]},"x8":{"rotate":[{"time":0,"angle":-40.8,"curve":"stepped"},{"time":0.6,"angle":-40.8},{"time":0.6667,"angle":14.4},{"time":1.4667,"angle":-40.8}],"translate":[{"time":0.6667,"x":28.97,"y":11.85},{"time":1.4,"x":58.68,"y":-50.29}],"scale":[{"time":0.6667,"x":0.6,"y":0.6},{"time":1.4,"x":0,"y":0,"curve":"stepped"},{"time":1.4667,"x":0,"y":0}]},"20":{"translate":[{"time":0.6667,"x":0,"y":0},{"time":1.2667,"x":642.02,"y":0,"curve":"stepped"},{"time":1.4667,"x":642.02,"y":0}]},"21":{"translate":[{"time":0.6667,"x":0,"y":0},{"time":1.2667,"x":-525.91,"y":0,"curve":"stepped"},{"time":1.4667,"x":-525.91,"y":0}]},"22":{"translate":[{"time":0.6667,"x":0,"y":0},{"time":1.2667,"x":-517.71,"y":0,"curve":"stepped"},{"time":1.4667,"x":-517.71,"y":0}]},"14":{"translate":[{"time":0.6667,"x":0,"y":0},{"time":1.2667,"x":434.39,"y":0,"curve":"stepped"},{"time":1.4667,"x":434.39,"y":0}]},"13":{"translate":[{"time":0.6667,"x":0,"y":0},{"time":1.2667,"x":549.13,"y":0,"curve":"stepped"},{"time":1.4667,"x":549.13,"y":0}]},"x5":{"rotate":[{"time":0.6667,"angle":0},{"time":1.4667,"angle":-56.4}],"translate":[{"time":0,"x":69.4,"y":23.98},{"time":1.4667,"x":117.59,"y":-81.52}],"scale":[{"time":0,"x":0.84,"y":0.84,"curve":"stepped"},{"time":0.8333,"x":0.84,"y":0.84},{"time":1.3333,"x":0,"y":0,"curve":"stepped"},{"time":1.4667,"x":0,"y":0}]},"x6":{"rotate":[{"time":0.6667,"angle":25.2},{"time":1.4667,"angle":-43.2}],"translate":[{"time":0.6667,"x":0,"y":0},{"time":1.4667,"x":-9.21,"y":-77.12}],"scale":[{"time":0.6667,"x":1,"y":1},{"time":1.0667,"x":0.72,"y":0.72},{"time":1.4667,"x":0,"y":0}]},"x17":{"rotate":[{"time":0,"angle":-15.6,"curve":"stepped"},{"time":0.6333,"angle":-15.6},{"time":0.6667,"angle":-58.8},{"time":1.4667,"angle":-33.3}],"translate":[{"time":0.6667,"x":0,"y":0},{"time":1.4667,"x":47.55,"y":-15.45}],"scale":[{"time":0,"x":0,"y":0,"curve":"stepped"},{"time":0.6333,"x":0,"y":0},{"time":0.6667,"x":0.7,"y":0.7},{"time":1,"x":0.52,"y":0.46},{"time":1.4333,"x":0,"y":0,"curve":"stepped"},{"time":1.4667,"x":0,"y":0}]},"x18":{"rotate":[{"time":0,"angle":-40.8,"curve":"stepped"},{"time":0.6,"angle":-40.8},{"time":0.6667,"angle":14.4},{"time":1.4667,"angle":-40.8}],"translate":[{"time":0.6667,"x":28.97,"y":11.85},{"time":1.4,"x":58.68,"y":-50.29}],"scale":[{"time":0.6667,"x":0.6,"y":0.6},{"time":1.4,"x":0,"y":0,"curve":"stepped"},{"time":1.4667,"x":0,"y":0}]},"x16":{"rotate":[{"time":0,"angle":144,"curve":"stepped"},{"time":0.6667,"angle":144},{"time":1.0667,"angle":249.6},{"time":1.4667,"angle":-26.4}],"translate":[{"time":0,"x":-85.62,"y":-133.24,"curve":"stepped"},{"time":0.6667,"x":-85.62,"y":-133.24},{"time":1.4667,"x":173.13,"y":232.59}]},"x20":{"rotate":[{"time":0.6667,"angle":0},{"time":1.4667,"angle":-56.4}],"translate":[{"time":0,"x":69.4,"y":23.98},{"time":1.4667,"x":117.59,"y":-81.52}],"scale":[{"time":0,"x":0.84,"y":0.84,"curve":"stepped"},{"time":0.8333,"x":0.84,"y":0.84},{"time":1.2,"x":0,"y":0,"curve":"stepped"},{"time":1.4667,"x":0,"y":0}]},"x21":{"rotate":[{"time":0.6667,"angle":25.2},{"time":1.4667,"angle":-43.2}],"translate":[{"time":0.6667,"x":0,"y":0},{"time":1.4667,"x":-42.73,"y":-76.33}],"scale":[{"time":0.6667,"x":1,"y":1},{"time":1.0667,"x":0.72,"y":0.72},{"time":1.4667,"x":0,"y":0}]},"x19":{"rotate":[{"time":0,"angle":177.6}],"translate":[{"time":0,"x":-9.96,"y":-143.78,"curve":"stepped"},{"time":0.6667,"x":-9.96,"y":-143.78},{"time":1.4667,"x":381.32,"y":-89.78}]},"x23":{"rotate":[{"time":0,"angle":-15.6,"curve":"stepped"},{"time":0.6333,"angle":-15.6},{"time":0.6667,"angle":-58.8},{"time":1.4667,"angle":-33.3}],"translate":[{"time":0.6667,"x":0,"y":0},{"time":1.4667,"x":47.55,"y":-15.45}],"scale":[{"time":0,"x":0,"y":0,"curve":"stepped"},{"time":0.6333,"x":0,"y":0},{"time":0.6667,"x":0.7,"y":0.7},{"time":1,"x":0.52,"y":0.46},{"time":1.2667,"x":0,"y":0,"curve":"stepped"},{"time":1.4667,"x":0,"y":0}]},"x24":{"rotate":[{"time":0,"angle":-40.8,"curve":"stepped"},{"time":0.6,"angle":-40.8},{"time":0.6667,"angle":14.4},{"time":1.4667,"angle":-40.8}],"translate":[{"time":0.6667,"x":28.97,"y":11.85},{"time":1.4,"x":58.68,"y":-50.29}],"scale":[{"time":0.6667,"x":0.6,"y":0.6},{"time":1.4,"x":0,"y":0,"curve":"stepped"},{"time":1.4667,"x":0,"y":0}]},"x22":{"rotate":[{"time":0,"angle":144,"curve":"stepped"},{"time":0.6667,"angle":144},{"time":1.0667,"angle":249.6},{"time":1.4667,"angle":-26.4}],"translate":[{"time":0,"x":-85.62,"y":-133.24,"curve":"stepped"},{"time":0.6667,"x":-85.62,"y":-133.24},{"time":1.4667,"x":427.08,"y":-87.58}]},"x26":{"rotate":[{"time":0.6667,"angle":0},{"time":1.4667,"angle":-56.4}],"translate":[{"time":0,"x":69.4,"y":23.98},{"time":1.4667,"x":117.59,"y":-81.52}],"scale":[{"time":0,"x":0.84,"y":0.84,"curve":"stepped"},{"time":0.8333,"x":0.84,"y":0.84},{"time":1.3333,"x":0,"y":0,"curve":"stepped"},{"time":1.4667,"x":0,"y":0}]},"x27":{"rotate":[{"time":0.6667,"angle":25.2},{"time":1.4667,"angle":-43.2}],"translate":[{"time":0.6667,"x":0,"y":0},{"time":1.4667,"x":-42.73,"y":-76.33}],"scale":[{"time":0.6667,"x":1,"y":1},{"time":1.0667,"x":0.72,"y":0.72},{"time":1.4667,"x":0,"y":0}]},"x25":{"rotate":[{"time":0,"angle":177.6}],"translate":[{"time":0,"x":-9.96,"y":-143.78,"curve":"stepped"},{"time":0.6667,"x":-9.96,"y":-143.78},{"time":1.4667,"x":-344.76,"y":-309.48}]},"x29":{"rotate":[{"time":0,"angle":-15.6,"curve":"stepped"},{"time":0.6333,"angle":-15.6},{"time":0.6667,"angle":-58.8},{"time":1.4667,"angle":-33.3}],"translate":[{"time":0.6667,"x":0,"y":0},{"time":1.4667,"x":47.55,"y":-15.45}],"scale":[{"time":0,"x":0,"y":0,"curve":"stepped"},{"time":0.6333,"x":0,"y":0},{"time":0.6667,"x":0.7,"y":0.7},{"time":1,"x":0.52,"y":0.46},{"time":1.2667,"x":0,"y":0,"curve":"stepped"},{"time":1.4667,"x":0,"y":0}]},"x30":{"rotate":[{"time":0,"angle":-40.8,"curve":"stepped"},{"time":0.6,"angle":-40.8},{"time":0.6667,"angle":14.4},{"time":1.4667,"angle":-40.8}],"translate":[{"time":0.6667,"x":28.97,"y":11.85},{"time":1.4,"x":58.68,"y":-50.29}],"scale":[{"time":0.6667,"x":0.6,"y":0.6},{"time":1.4,"x":0,"y":0,"curve":"stepped"},{"time":1.4667,"x":0,"y":0}]},"x28":{"rotate":[{"time":0,"angle":144,"curve":"stepped"},{"time":0.6667,"angle":144},{"time":1.0667,"angle":249.6},{"time":1.4667,"angle":-26.4}],"translate":[{"time":0,"x":-8.3,"y":-149.55,"curve":"stepped"},{"time":0.6667,"x":-8.3,"y":-149.55},{"time":1.4667,"x":-384.79,"y":176.16}]},"x32":{"rotate":[{"time":0,"angle":-15.6,"curve":"stepped"},{"time":0.6333,"angle":-15.6},{"time":0.6667,"angle":-58.8},{"time":1.4667,"angle":-33.3}],"translate":[{"time":0.6667,"x":0,"y":0},{"time":1.4667,"x":47.55,"y":-15.45}],"scale":[{"time":0,"x":0,"y":0,"curve":"stepped"},{"time":0.6333,"x":0,"y":0},{"time":0.6667,"x":0.7,"y":0.7},{"time":1,"x":0.52,"y":0.46},{"time":1.2667,"x":0,"y":0,"curve":"stepped"},{"time":1.4667,"x":0,"y":0}]},"x33":{"rotate":[{"time":0,"angle":-40.8,"curve":"stepped"},{"time":0.6,"angle":-40.8},{"time":0.6667,"angle":14.4},{"time":1.4667,"angle":-40.8}],"translate":[{"time":0.6667,"x":28.97,"y":11.85},{"time":1.4,"x":58.68,"y":-50.29}],"scale":[{"time":0.6667,"x":0.6,"y":0.6},{"time":1.4,"x":0,"y":0,"curve":"stepped"},{"time":1.4667,"x":0,"y":0}]},"x31":{"rotate":[{"time":0,"angle":144,"curve":"stepped"},{"time":0.6667,"angle":144},{"time":1.0667,"angle":249.6},{"time":1.4667,"angle":-26.4}],"translate":[{"time":0,"x":-1.34,"y":-76.2,"curve":"stepped"},{"time":0.6667,"x":-1.34,"y":-76.2},{"time":1.4667,"x":-78.07,"y":279.83}]},"x35":{"rotate":[{"time":0,"angle":-15.6,"curve":"stepped"},{"time":0.6333,"angle":-15.6},{"time":0.6667,"angle":-58.8},{"time":1.4667,"angle":-33.3}],"translate":[{"time":0.6667,"x":0,"y":0},{"time":1.4667,"x":47.55,"y":-15.45}],"scale":[{"time":0,"x":0,"y":0,"curve":"stepped"},{"time":0.6333,"x":0,"y":0},{"time":0.6667,"x":0.7,"y":0.7},{"time":1,"x":0.52,"y":0.46},{"time":1.2667,"x":0,"y":0,"curve":"stepped"},{"time":1.4667,"x":0,"y":0}]},"x36":{"rotate":[{"time":0,"angle":-40.8,"curve":"stepped"},{"time":0.6,"angle":-40.8},{"time":0.6667,"angle":14.4},{"time":1.4667,"angle":-40.8}],"translate":[{"time":0.6667,"x":28.97,"y":11.85},{"time":1.4,"x":58.68,"y":-50.29}],"scale":[{"time":0.6667,"x":0.6,"y":0.6},{"time":1.4,"x":0,"y":0,"curve":"stepped"},{"time":1.4667,"x":0,"y":0}]},"x34":{"rotate":[{"time":0,"angle":144,"curve":"stepped"},{"time":0.6667,"angle":144},{"time":1.0667,"angle":249.6},{"time":1.4667,"angle":-26.4}],"translate":[{"time":0,"x":-50.72,"y":-13.97,"curve":"stepped"},{"time":0.6667,"x":-50.72,"y":-13.97},{"time":1.4667,"x":-247.63,"y":-292.88}]},"x38":{"rotate":[{"time":0,"angle":-15.6,"curve":"stepped"},{"time":0.6333,"angle":-15.6},{"time":0.6667,"angle":-58.8},{"time":1.4667,"angle":-33.3}],"translate":[{"time":0.6667,"x":0,"y":0},{"time":1.4667,"x":47.55,"y":-15.45}],"scale":[{"time":0,"x":0,"y":0,"curve":"stepped"},{"time":0.6333,"x":0,"y":0},{"time":0.6667,"x":0.7,"y":0.7},{"time":1,"x":0.52,"y":0.46},{"time":1.2667,"x":0,"y":0,"curve":"stepped"},{"time":1.4667,"x":0,"y":0}]},"x39":{"rotate":[{"time":0,"angle":-40.8,"curve":"stepped"},{"time":0.6,"angle":-40.8},{"time":0.6667,"angle":14.4},{"time":1.4667,"angle":-40.8}],"translate":[{"time":0.6667,"x":28.97,"y":11.85},{"time":1.4,"x":58.68,"y":-50.29}],"scale":[{"time":0.6667,"x":0.6,"y":0.6},{"time":1.4,"x":0,"y":0,"curve":"stepped"},{"time":1.4667,"x":0,"y":0}]},"x37":{"rotate":[{"time":0,"angle":144,"curve":"stepped"},{"time":0.6667,"angle":144},{"time":1.0667,"angle":249.6},{"time":1.4667,"angle":-26.4}],"translate":[{"time":0,"x":-85.62,"y":-133.24,"curve":"stepped"},{"time":0.6667,"x":-85.62,"y":-133.24},{"time":1.4667,"x":-64.19,"y":-279.25}]},"x41":{"rotate":[{"time":0,"angle":-15.6,"curve":"stepped"},{"time":0.6333,"angle":-15.6},{"time":0.6667,"angle":-58.8},{"time":1.4667,"angle":-33.3}],"translate":[{"time":0.6667,"x":0,"y":0},{"time":1.4667,"x":47.55,"y":-15.45}],"scale":[{"time":0,"x":0,"y":0,"curve":"stepped"},{"time":0.6333,"x":0,"y":0},{"time":0.6667,"x":0.7,"y":0.7},{"time":1,"x":0.52,"y":0.46},{"time":1.2667,"x":0,"y":0,"curve":"stepped"},{"time":1.4667,"x":0,"y":0}]},"x42":{"rotate":[{"time":0,"angle":-40.8,"curve":"stepped"},{"time":0.6,"angle":-40.8},{"time":0.6667,"angle":14.4},{"time":1.4667,"angle":-40.8}],"translate":[{"time":0.6667,"x":28.97,"y":11.85},{"time":1.4,"x":58.68,"y":-50.29}],"scale":[{"time":0.6667,"x":0.6,"y":0.6},{"time":1.4,"x":0,"y":0,"curve":"stepped"},{"time":1.4667,"x":0,"y":0}]},"x40":{"rotate":[{"time":0,"angle":144,"curve":"stepped"},{"time":0.6667,"angle":144},{"time":1.0667,"angle":249.6},{"time":1.4667,"angle":-26.4}],"translate":[{"time":0,"x":-46.33,"y":-45.52,"curve":"stepped"},{"time":0.6667,"x":-46.33,"y":-45.52},{"time":1.4667,"x":-322.52,"y":276.9}]},"x44":{"rotate":[{"time":0.6667,"angle":0},{"time":1.4667,"angle":-56.4}],"translate":[{"time":0,"x":69.4,"y":23.98},{"time":1.4667,"x":117.59,"y":-81.52}],"scale":[{"time":0,"x":0.84,"y":0.84,"curve":"stepped"},{"time":0.8333,"x":0.84,"y":0.84},{"time":1.3333,"x":0,"y":0,"curve":"stepped"},{"time":1.4667,"x":0,"y":0}]},"x45":{"rotate":[{"time":0.6667,"angle":25.2},{"time":1.4667,"angle":-43.2}],"translate":[{"time":0.6667,"x":0,"y":0},{"time":1.4667,"x":-42.73,"y":-76.33}],"scale":[{"time":0.6667,"x":1,"y":1},{"time":1.0667,"x":0.72,"y":0.72},{"time":1.4667,"x":0,"y":0}]},"x43":{"rotate":[{"time":0,"angle":177.6}],"translate":[{"time":0,"x":-122.08,"y":-54.93,"curve":"stepped"},{"time":0.6667,"x":-122.08,"y":-54.93},{"time":1.4667,"x":332.92,"y":-246.58}]},"x47":{"rotate":[{"time":0.6667,"angle":0},{"time":1.4667,"angle":-56.4}],"translate":[{"time":0,"x":69.4,"y":23.98},{"time":1.4667,"x":117.59,"y":-81.52}],"scale":[{"time":0,"x":0.84,"y":0.84,"curve":"stepped"},{"time":0.8333,"x":0.84,"y":0.84},{"time":1.2333,"x":0,"y":0,"curve":"stepped"},{"time":1.4667,"x":0,"y":0}]},"x48":{"rotate":[{"time":0.6667,"angle":25.2},{"time":1.4667,"angle":-43.2}],"translate":[{"time":0.6667,"x":0,"y":0},{"time":1.4667,"x":-42.73,"y":-76.33}],"scale":[{"time":0.6667,"x":1,"y":1},{"time":1.0667,"x":0.72,"y":0.72},{"time":1.4667,"x":0,"y":0}]},"x46":{"rotate":[{"time":0,"angle":177.6}],"translate":[{"time":0,"x":-9.96,"y":-143.78,"curve":"stepped"},{"time":0.6667,"x":-9.96,"y":-143.78},{"time":1.4667,"x":361.27,"y":36.94}]},"x50":{"rotate":[{"time":0.6667,"angle":0},{"time":1.4667,"angle":-56.4}],"translate":[{"time":0,"x":69.4,"y":23.98},{"time":1.4667,"x":117.59,"y":-81.52}],"scale":[{"time":0,"x":0.84,"y":0.84,"curve":"stepped"},{"time":0.8333,"x":0.84,"y":0.84},{"time":1.3333,"x":0,"y":0,"curve":"stepped"},{"time":1.4667,"x":0,"y":0}]},"x51":{"rotate":[{"time":0.6667,"angle":25.2},{"time":1.4667,"angle":-43.2}],"translate":[{"time":0.6667,"x":0,"y":0},{"time":1.4667,"x":-42.73,"y":-76.33}],"scale":[{"time":0.6667,"x":1,"y":1},{"time":1.0667,"x":0.72,"y":0.72},{"time":1.4667,"x":0,"y":0}]},"x49":{"rotate":[{"time":0,"angle":177.6}],"translate":[{"time":0,"x":-9.96,"y":-143.78,"curve":"stepped"},{"time":0.6667,"x":-9.96,"y":-143.78},{"time":1.4667,"x":175.2,"y":191.41}]},"x53":{"rotate":[{"time":0.6667,"angle":0},{"time":1.4667,"angle":-56.4}],"translate":[{"time":0,"x":69.4,"y":23.98},{"time":1.4667,"x":117.59,"y":-81.52}],"scale":[{"time":0,"x":0.84,"y":0.84,"curve":"stepped"},{"time":0.8333,"x":0.84,"y":0.84},{"time":1.3333,"x":0,"y":0,"curve":"stepped"},{"time":1.4667,"x":0,"y":0}]},"x54":{"rotate":[{"time":0.6667,"angle":25.2},{"time":1.4667,"angle":-43.2}],"translate":[{"time":0.6667,"x":0,"y":0},{"time":1.4667,"x":-42.73,"y":-76.33}],"scale":[{"time":0.6667,"x":1,"y":1},{"time":1.0667,"x":0.72,"y":0.72},{"time":1.4667,"x":0,"y":0}]},"x52":{"rotate":[{"time":0,"angle":177.6}],"translate":[{"time":0,"x":-24,"y":-128,"curve":"stepped"},{"time":0.6667,"x":-24,"y":-128},{"time":1.4667,"x":-390.96,"y":-291.88}]},"x56":{"rotate":[{"time":0.6667,"angle":0},{"time":1.4667,"angle":-56.4}],"translate":[{"time":0,"x":69.4,"y":23.98},{"time":1.4667,"x":117.59,"y":-81.52}],"scale":[{"time":0,"x":0.84,"y":0.84,"curve":"stepped"},{"time":0.8333,"x":0.84,"y":0.84},{"time":1.3333,"x":0,"y":0,"curve":"stepped"},{"time":1.4667,"x":0,"y":0}]},"x57":{"rotate":[{"time":0.6667,"angle":25.2},{"time":1.4667,"angle":-43.2}],"translate":[{"time":0.6667,"x":0,"y":0},{"time":1.4667,"x":-42.73,"y":-76.33}],"scale":[{"time":0.6667,"x":1,"y":1},{"time":1.0667,"x":0.72,"y":0.72},{"time":1.4667,"x":0,"y":0}]},"x55":{"rotate":[{"time":0,"angle":177.6}],"translate":[{"time":0,"x":-9.96,"y":-143.78,"curve":"stepped"},{"time":0.6667,"x":-9.96,"y":-143.78},{"time":1.4667,"x":-246.76,"y":304.58}]},"x59":{"rotate":[{"time":0.6667,"angle":0},{"time":1.4667,"angle":-56.4}],"translate":[{"time":0,"x":69.4,"y":23.98},{"time":1.4667,"x":117.59,"y":-81.52}],"scale":[{"time":0,"x":0.84,"y":0.84,"curve":"stepped"},{"time":0.8333,"x":0.84,"y":0.84},{"time":1.1667,"x":0,"y":0,"curve":"stepped"},{"time":1.4667,"x":0,"y":0}]},"x60":{"rotate":[{"time":0.6667,"angle":25.2},{"time":1.4667,"angle":-43.2}],"translate":[{"time":0.6667,"x":0,"y":0},{"time":1.4667,"x":-42.73,"y":-76.33}],"scale":[{"time":0.6667,"x":1,"y":1},{"time":1.0667,"x":0.72,"y":0.72},{"time":1.4667,"x":0,"y":0}]},"x58":{"rotate":[{"time":0,"angle":177.6}],"translate":[{"time":0,"x":32.5,"y":-77.76,"curve":"stepped"},{"time":0.6667,"x":32.5,"y":-77.76},{"time":1.4667,"x":-366.26,"y":153.72}]}}}}}