{"frameRate":24,"name":"qiandaoteshu1","version":"5.5","compatibleVersion":"5.5","armature":[{"type":"Armature","frameRate":24,"name":"armatureName","aabb":{"x":-109,"y":-153,"width":219,"height":306},"bone":[{"name":"root"},{"name":"qiandao2","parent":"root"}],"slot":[{"name":"keqiandao2","parent":"qiandao2"},{"blendMode":"add","name":"keqiandao21","parent":"qiandao2"}],"skin":[{"slot":[{"name":"keqiandao2","display":[{"name":"keqiandao2","transform":{"x":0.5}}]},{"name":"keqiandao21","display":[{"name":"keqiandao2","transform":{"x":0.5}}]}]}],"animation":[{"duration":44,"playTimes":0,"name":"newAnimation_qiandao2","bone":[{"name":"qiandao2","translateFrame":[{"duration":2,"tweenEasing":0,"y":-14.51},{"duration":2,"tweenEasing":0,"y":-20.12},{"duration":40}],"scaleFrame":[{"duration":4,"curve":[0,0,0.5,1],"x":2.4,"y":2.4},{"duration":40}]}],"slot":[{"name":"keqiandao2","colorFrame":[{"duration":4,"tweenEasing":0,"value":{"aM":0}},{"duration":40}]},{"name":"keqiandao21","colorFrame":[{"duration":24,"tweenEasing":0,"value":{"aM":0}},{"duration":10,"tweenEasing":0,"value":{"aM":0}},{"duration":10,"tweenEasing":0,"value":{"aM":15}},{"duration":0,"value":{"aM":0}}]}]},{"duration":60,"playTimes":0,"name":"newAnimation_qiandao_xunhuan_2","slot":[{"name":"keqiandao21","colorFrame":[{"duration":20,"tweenEasing":0,"value":{"aM":0}},{"duration":10,"tweenEasing":0,"value":{"aM":0}},{"duration":10,"tweenEasing":0,"value":{"aM":15}},{"duration":10,"tweenEasing":0,"value":{"aM":0}},{"duration":10,"tweenEasing":0,"value":{"aM":15}},{"duration":0,"value":{"aM":0}}]}]}],"defaultActions":[{"gotoAndPlay":"newAnimation_qiandao2"}]}]}