{"frameRate":24,"name":"fansanguang","version":"5.5","compatibleVersion":"5.5","armature":[{"type":"Armature","frameRate":24,"name":"Armature","aabb":{"x":-327.25,"y":-363.25,"width":655.5,"height":729.5},"bone":[{"name":"root"},{"length":31,"name":"img_2","parent":"root","transform":{"x":-0.5,"y":-0.5}},{"length":31.5,"name":"img_61","parent":"root","transform":{"x":0.5,"skX":-1.8183,"skY":-1.8183}},{"length":39.5,"name":"img_3","parent":"root","transform":{"x":0.5,"skX":2.1747,"skY":2.1747}}],"slot":[{"blendMode":"add","name":"img_2","parent":"img_2"},{"blendMode":"add","name":"img_4","parent":"img_61"},{"blendMode":"add","name":"img_3","parent":"img_3","color":{"gM":82,"bM":18}}],"skin":[{"slot":[{"name":"img_4","display":[{"name":"img_4","transform":{"x":-0.55,"y":1.48,"skX":1.82,"skY":1.82}}]},{"name":"img_2","display":[{"name":"img_2","transform":{"x":-9.5,"y":-15.5}}]},{"name":"img_3","display":[{"name":"img_3","transform":{"skX":-2.17,"skY":-2.17}}]}]}],"animation":[{"duration":13,"playTimes":0,"name":"newAnimation","bone":[{"name":"img_2","rotateFrame":[{"duration":13,"tweenEasing":0},{"duration":0,"rotate":30}],"scaleFrame":[{"duration":6,"tweenEasing":0,"x":0.7,"y":0.7},{"duration":7,"x":2.25,"y":2.25}]},{"name":"img_61","scaleFrame":[{"duration":4,"tweenEasing":0,"x":0.3,"y":0.3},{"duration":9,"x":0.55,"y":0.55}]},{"name":"img_3","scaleFrame":[{"duration":4,"tweenEasing":0,"x":0.2,"y":0.2},{"duration":9,"x":2.9,"y":2.9}]}],"slot":[{"name":"img_2","colorFrame":[{"duration":6,"tweenEasing":0,"value":{"aM":0}},{"duration":7,"tweenEasing":0},{"duration":0,"value":{"aM":0}}]},{"name":"img_4","colorFrame":[{"duration":2,"tweenEasing":0,"value":{"aM":0}},{"duration":4,"tweenEasing":0,"value":{"aM":23}},{"duration":7,"value":{"aM":0}}]},{"name":"img_3","colorFrame":[{"duration":2,"tweenEasing":0,"value":{"aM":0,"gM":93,"bM":40}},{"duration":2,"tweenEasing":0,"value":{"aM":40,"gM":93,"bM":40}},{"duration":9,"value":{"aM":0,"gM":93,"bM":40}}]}]}],"defaultActions":[{"gotoAndPlay":"newAnimation"}]}]}